{
    "success": {
        "total": 1
    },
    "contents": {
        "quotes": [
            {
                "quote": "Those who know how to win are much more numerous than those who know how to make proper use of their victories",
                "length": "110",
                "author": "Polybius",
                "tags": [
                    "inspire",
                    "winning"
                ],
                "category": "inspire",
                "date": "2017-12-18",
                "permalink": "https://theysaidso.com/quote/Pa0wzJ6f7UsH91Ttr2kmHweF/polybius-those-who-know-how-to-win-are-much-more-numerous-than-those-who-know-ho",
                "title": "Inspiring Quote of the day",
                "background": "https://theysaidso.com/img/bgs/man_on_the_mountain.jpg",
                "id": "Pa0wzJ6f7UsH91Ttr2kmHweF"
            }
        ],
        "copyright": "2017-19 theysaidso.com"
    }
}